easonsi/__init__.py
easonsi/files/google_sheet/__init__.py
easonsi/files/google_sheet/connection.py
easonsi/files/google_sheet/test.py
easonsi/files/gsheet.py
easonsi/llm/__init__.py
easonsi/llm/formater.py
easonsi/llm/jinja_templates.py
easonsi/llm/llm_completion.py
easonsi/llm/model_utils.py
easonsi/llm/openai_client.py
easonsi/templates/data-process/xlsx.py
easonsi/templates/data-process/xml.etree.py
easonsi/templates/python-basic/encoding.py
easonsi/templates/python-utils.py
easonsi/templates/tensorboardX.py
easonsi/templates/util-modules/argparse.py
easonsi/templates/util-modules/logging.py
easonsi/templates/util-modules/time.py
easonsi/util/__init__.py
easonsi/util/file.py
easonsi/util/io.py
easonsi/util/leetcode.py
easonsi/util/network.py
easonsi/util/plot.py
easonsi/utils.py
easonsi-0.0.8.dist-info/LICENCE
easonsi-0.0.8.dist-info/METADATA
easonsi-0.0.8.dist-info/WHEEL
easonsi-0.0.8.dist-info/RECORD
