Metadata-Version: 2.1
Name: easonsi
Version: 0.0.8
Summary: A simple package utlized by easonsi
Author: Eason Shi
Author-email: oldcitystal@gmail.com
Requires-Python: >=3.10,<4.0
Classifier: Programming Language :: Python :: 3
Classifier: Programming Language :: Python :: 3.10
Classifier: Programming Language :: Python :: 3.11
Classifier: Programming Language :: Python :: 3.12
Classifier: Programming Language :: Python :: 3.13
Requires-Dist: sortedcontainers (>=2.4.0,<3.0.0)
